quercle/__init__.py
quercle/_base.py
quercle/async_client.py
quercle/client.py
quercle/descriptions.py
quercle/exceptions.py
quercle/py.typed
quercle-0.1.4.dist-info/METADATA
quercle-0.1.4.dist-info/WHEEL
quercle-0.1.4.dist-info/licenses/LICENSE
quercle-0.1.4.dist-info/RECORD
