Metadata-Version: 2.4
Name: quercle
Version: 0.1.4
Summary: Official Python SDK for the Quercle API - AI-powered web search and fetching
Project-URL: Homepage, https://quercle.dev
Project-URL: Documentation, https://quercle.dev/docs
Project-URL: Repository, https://github.com/quercledev/quercle-python
Author-email: Quercle <support@quercle.dev>
License: MIT
License-File: LICENSE
Keywords: ai,api,fetch,quercle,search,web
Classifier: Development Status :: 4 - Beta
Classifier: Intended Audience :: Developers
Classifier: License :: OSI Approved :: MIT License
Classifier: Programming Language :: Python :: 3
Classifier: Programming Language :: Python :: 3.10
Classifier: Programming Language :: Python :: 3.11
Classifier: Programming Language :: Python :: 3.12
Classifier: Typing :: Typed
Requires-Python: >=3.10
Requires-Dist: httpx>=0.27.0
Provides-Extra: dev
Requires-Dist: mypy>=1.10.0; extra == 'dev'
Requires-Dist: pytest-asyncio>=0.23.0; extra == 'dev'
Requires-Dist: pytest-cov>=4.1.0; extra == 'dev'
Requires-Dist: pytest>=8.0.0; extra == 'dev'
Requires-Dist: ruff>=0.4.0; extra == 'dev'
